thorunimore/__init__.py
thorunimore/database/__init__.py
thorunimore/database/base/__init__.py
thorunimore/database/students.py
thorunimore/database/telegram.py
thorunimore/database/tokens.py
thorunimore/deeplinking.py
thorunimore/telegram/__init__.py
thorunimore/telegram/__main__.py
thorunimore/telegram/challenges.py
thorunimore/telegram/dialog.py
thorunimore/web/__main__.py
thorunimore/web/static/style.css
thorunimore/web/static/style.css.map
thorunimore/web/static/style.less
thorunimore/web/templates/base.html
thorunimore/web/templates/error.html
thorunimore/web/templates/info.html
thorunimore/web/templates/longer.html
thorunimore/web/templates/privacy.html
thorunimore-1.2.13.dist-info/entry_points.txt
thorunimore-1.2.13.dist-info/LICENSE.txt
thorunimore-1.2.13.dist-info/WHEEL
thorunimore-1.2.13.dist-info/METADATA
thorunimore-1.2.13.dist-info/RECORD
