Metadata-Version: 2.1
Name: thorunimore
Version: 1.2.13
Summary: Authentication gateway bot for the Unimore Informatica Telegram group
Home-page: https://thor.steffo.eu/
License: AGPL-3.0-or-later
Keywords: telegram-bot,oauth2,flask-application,telethon-bot,unimore-informatica
Author: Stefano Pigozzi
Author-email: me@steffo.eu
Maintainer: Stefano Pigozzi
Maintainer-email: me@steffo.eu
Requires-Python: >=3.8,<3.9
Classifier: Framework :: Flask
Classifier: License :: OSI Approved :: GNU Affero General Public License v3 or later (AGPLv3+)
Classifier: Natural Language :: Italian
Classifier: Operating System :: OS Independent
Classifier: Programming Language :: Python :: 3
Classifier: Programming Language :: Python :: 3.8
Classifier: Topic :: Internet
Classifier: Topic :: Security
Requires-Dist: aiohttp (>=3.6.2,<4.0.0)
Requires-Dist: authlib (>=0.14.3,<0.15.0)
Requires-Dist: coloredlogs (>=14.0,<15.0)
Requires-Dist: cryptg (>=0.2.post1,<0.3)
Requires-Dist: flask (>=1.1.2,<2.0.0)
Requires-Dist: flask-sqlalchemy (>=2.4.4,<3.0.0)
Requires-Dist: gunicorn (>=20.1.0,<21.0.0)
Requires-Dist: itsdangerous (>=1.1.0,<2.0.0)
Requires-Dist: markupsafe (>=1,<2)
Requires-Dist: psycopg2 (>=2.9.3,<3.0.0)
Requires-Dist: requests (>=2.24.0,<3.0.0)
Requires-Dist: royalnet (==6.0.0a4)
Requires-Dist: telethon (>=1.16.4,<2.0.0)
Project-URL: Repository, https://github.com/Steffo99/thorunimore
